setup.py
SpiderTool/Browser.py
SpiderTool/Request.py
SpiderTool/__init__.py
SpiderTool.egg-info/PKG-INFO
SpiderTool.egg-info/SOURCES.txt
SpiderTool.egg-info/dependency_links.txt
SpiderTool.egg-info/requires.txt
SpiderTool.egg-info/top_level.txt