Metadata-Version: 1.0
Name: SpiderTool
Version: 19.4.1
Summary: The package for Spider
Home-page: https://github.com/lijiacaigit/SpiderTool
Author: Lijiacai
Author-email: 1050518702@qq.com
License: UNKNOWN
Keywords: pip,SpiderTool,spider,spidertool
Platform: any
